pyframe/__init__.py
pyframe/atoms.py
pyframe/fragments.py
pyframe/potentials.py
pyframe/process.py
pyframe/project.py
pyframe/readers.py
pyframe/regions.py
pyframe/system.py
pyframe/utils.py
pyframe/writers.py
pyframe/data/alep.csv
pyframe/data/cp3.csv
pyframe/data/ff03.csv
pyframe/data/ff94.csv
pyframe/data/lipid14.csv
pyframe/data/lipid17.csv
pyframe/data/sep.csv
pyframe/data/tip3p.csv
pyframe/tests/test_atoms.py
pyframe/tests/test_standard_potentials.py
pyframe/tests/test_utils.py
PyFraME-0.4.0.dist-info/LICENSE
PyFraME-0.4.0.dist-info/METADATA
PyFraME-0.4.0.dist-info/WHEEL
PyFraME-0.4.0.dist-info/top_level.txt
PyFraME-0.4.0.dist-info/RECORD
