Metadata-Version: 2.1
Name: PyFraME
Version: 0.4.0
Summary: PyFraME: Python framework for Fragment-based Multiscale Embedding
Home-page: https://gitlab.com/FraME-projects/PyFraME/
Author: Jógvan Magnus Haugaard Olsen and Peter Reinholdt
Author-email: jmho@kemi.dtu.dk
Maintainer: Jógvan Magnus Haugaard Olsen
Maintainer-email: jmho@kemi.dtu.dk
License: UNKNOWN
Download-URL: https://gitlab.com/FraME-projects/PyFraME/-/archive/0.4.0/PyFraME-0.4.0.zip
Project-URL: Zenodo deposit, https://doi.org/10.5281/zenodo.4899311
Project-URL: Issue Tracker, https://gitlab.com/FraME-projects/PyFraME/issues
Project-URL: Source, https://gitlab.com/FraME-projects/PyFraME/
Platform: UNKNOWN
Classifier: Intended Audience :: Science/Research
Classifier: License :: OSI Approved :: GNU General Public License v3 or later (GPLv3+)
Classifier: Natural Language :: English
Classifier: Programming Language :: Python :: 3.7
Classifier: Programming Language :: Python :: 3.8
Classifier: Programming Language :: Python :: 3.9
Classifier: Topic :: Scientific/Engineering :: Chemistry
Classifier: Topic :: Scientific/Engineering :: Physics
Requires-Python: >=3.7
License-File: LICENSE
Requires-Dist: daltools
Requires-Dist: h5py
Requires-Dist: loprop
Requires-Dist: numpy
Requires-Dist: scipy
